pyora/Blend.py
pyora/BlendNonSep.py
pyora/Composite.py
pyora/Layer.py
pyora/OpenRasterProject.py
pyora/Project.py
pyora/Render.py
pyora/__init__.py
pyora-0.3.11.dist-info/LICENSE
pyora-0.3.11.dist-info/METADATA
pyora-0.3.11.dist-info/WHEEL
pyora-0.3.11.dist-info/top_level.txt
pyora-0.3.11.dist-info/RECORD
