Metadata-Version: 2.1
Name: pyora
Version: 0.3.11
Summary: Read, Write, and Render OpenRaster (.ORA) files
Home-page: https://gitlab.com/inklabapp/pyora
Author: InkLab
Author-email: inklabapp@gmail.com
License: MIT License
Platform: UNKNOWN
Classifier: Programming Language :: Python :: 3
Classifier: License :: OSI Approved :: MIT License
Classifier: Operating System :: OS Independent
Requires-Dist: pillow
Requires-Dist: numpy
Requires-Dist: defusedxml
